_testing/__init__.py
_testing/environment.py
invoke_containers-0.2.0.dist-info/METADATA
invoke_containers-0.2.0.dist-info/WHEEL
invoke_containers/__init__.py
invoke_containers/env.py
invoke_containers-0.2.0.dist-info/RECORD
