Metadata-Version: 2.1
Name: invoke-containers
Version: 0.2.0
Summary: Invoke your tasks within containers.
Author-Email: jonjitsu <jonjitsu@codewarrior.ca>
License: MIT
Requires-Python: >=3.10
Requires-Dist: invoke>=2.2.0
